classypandas/__init__.py
classypandas/core.py
classypandas-0.1.dist-info/LICENSE
classypandas-0.1.dist-info/METADATA
classypandas-0.1.dist-info/WHEEL
classypandas-0.1.dist-info/top_level.txt
classypandas-0.1.dist-info/RECORD
