Metadata-Version: 2.1
Name: classypandas
Version: 0.1
Summary: Quickly annotate/label your data using jupyter widgets and pandas.
Home-page: https://github.com/TMMV/classypandas
Author: Tiago Vieira
Author-email: email@tiagovieira.pt
License: MIT
Platform: UNKNOWN
Classifier: Programming Language :: Python :: 3
Classifier: License :: OSI Approved :: MIT License
Classifier: Operating System :: OS Independent
Classifier: Framework :: Jupyter
Classifier: Topic :: Scientific/Engineering
Requires-Python: >=3.6
Requires-Dist: pandas (>=1.0.0)
Requires-Dist: jupyter (>=1.0.0)
Requires-Dist: ipywidgets (>=7.5.1)
